susee/__init__.py
susee/see_comm.py
susee/see_db.py
susee/see_dict.py
susee/see_drivers.py
susee/see_functions.py
susee-1.7.4.dist-info/LICENSE
susee-1.7.4.dist-info/METADATA
susee-1.7.4.dist-info/WHEEL
susee-1.7.4.dist-info/top_level.txt
susee-1.7.4.dist-info/RECORD
