Metadata-Version: 2.1
Name: susee
Version: 1.7.4
Summary: suSEE - Energy Monitoring Platform
Home-page: https://github.com/frlovecchio/susee
Author: eng. F.S. Lovecchio, ph.D - Bari, Italy
Author-email: frlovecchio@outlook.it
License: UNKNOWN
Platform: UNKNOWN
Classifier: Programming Language :: Python :: 3.5
Classifier: Programming Language :: Python :: 3.9
Classifier: License :: OSI Approved :: MIT License
Classifier: Operating System :: OS Independent
Classifier: Topic :: System :: Monitoring
Classifier: Topic :: Scientific/Engineering :: Information Analysis
Classifier: Topic :: Software Development :: User Interfaces
Requires-Python: >=3.5.0
License-File: LICENSE
Requires-Dist: numpy
Requires-Dist: pandas
Requires-Dist: mysql-connector
Requires-Dist: pymodbus
Requires-Dist: pytz
Requires-Dist: scipy
Requires-Dist: statsmodels
Requires-Dist: python-decouple
Requires-Dist: setuptools
Requires-Dist: wheel
